peft_ser/__init__.py
peft_ser/example.py
peft_ser/model/__init__.py
peft_ser/model/adapter.py
peft_ser/model/mms.py
peft_ser/model/wav2vec.py
peft_ser/model/wavlm_large.py
peft_ser/model/wavlm_plus.py
peft_ser/model/whisper.py
peft_ser-0.0.5.dist-info/LICENSE
peft_ser-0.0.5.dist-info/METADATA
peft_ser-0.0.5.dist-info/WHEEL
peft_ser-0.0.5.dist-info/top_level.txt
peft_ser-0.0.5.dist-info/RECORD
