Metadata-Version: 2.1
Name: peft-ser
Version: 0.0.5
Summary: Parameter Efficient Fine-tuning on Speech Emotion Recognition.
Author: Tiantian Feng
Author-email: Tiantian Feng <tiantiaf@usc.edu>
License: BSD License
Project-URL: Homepage, https://github.com/usc-sail/peft-ser
Project-URL: Bug Tracker, https://github.com/usc-sail/peft-ser/issues
Classifier: Programming Language :: Python :: 3
Classifier: License :: OSI Approved :: BSD License
Requires-Python: >=3.8
License-File: LICENSE
Provides-Extra: dev
Requires-Dist: pytest ; extra == 'dev'
Requires-Dist: scipy ; extra == 'dev'
Requires-Dist: black ; extra == 'dev'
Requires-Dist: flake8 ; extra == 'dev'
Requires-Dist: isort ; extra == 'dev'
